aio_alf-0.1.3.dist-info/DESCRIPTION.rst
aio_alf-0.1.3.dist-info/METADATA
aio_alf-0.1.3.dist-info/RECORD
aio_alf-0.1.3.dist-info/WHEEL
aio_alf-0.1.3.dist-info/metadata.json
aio_alf-0.1.3.dist-info/top_level.txt
aioalf/__init__.py
aioalf/client.py
aioalf/manager.py
aioalf/token.py
