Metadata-Version: 2.0
Name: aio-alf
Version: 0.1.3
Summary: OAuth Client For aiohttp
Home-page: https://github.com/globocom/aio-alf
Author: Globo.com
Author-email: entretenimento1@corp.globo.com
License: MIT
Keywords: oauth client client_credentials aiohtpp
Platform: UNKNOWN
Classifier: Development Status :: 4 - Beta
Classifier: Intended Audience :: Developers
Classifier: License :: OSI Approved :: MIT License
Classifier: Natural Language :: English
Classifier: Operating System :: MacOS
Classifier: Operating System :: POSIX
Classifier: Operating System :: Unix
Classifier: Operating System :: OS Independent
Classifier: Programming Language :: Python :: 3.6
Requires-Dist: aiohttp (>=2.3.0)
Provides-Extra: tests
Requires-Dist: mock; extra == 'tests'
Requires-Dist: asynctest; extra == 'tests'
Requires-Dist: bumpversion; extra == 'tests'
Requires-Dist: nose; extra == 'tests'
Requires-Dist: coverage; extra == 'tests'
Requires-Dist: yanc; extra == 'tests'
Requires-Dist: ipdb; extra == 'tests'
Requires-Dist: tox; extra == 'tests'
Requires-Dist: flake8; extra == 'tests'
